{"id":"analyticsdata\/v1alpha\/entity","type":"","title":"Google\\Analytics\\Data\\V1alpha\\Entity","name":"Entity","description":"<p>The unique identifier of the property whose events are tracked.<\/p>\n<p>Generated from protobuf message <code>google.analytics.data.v1alpha.Entity<\/code><\/p>\n<p>Extends <a href=\"https:\/\/github.com\/protocolbuffers\/protobuf-php\/tree\/v3.21.10\/src\/Google\/Protobuf\/Internal\/Message.php\" target=\"_blank\">Google\\Protobuf\\Internal\\Message<\/a><\/p>","examples":[],"resources":[],"methods":[]}