{"id":"dataflow\/v1beta3\/customsourcelocation","type":"","title":"Google\\Cloud\\Dataflow\\V1beta3\\CustomSourceLocation","name":"CustomSourceLocation","description":"<p>Identifies the location of a custom souce.<\/p>\n<p>Generated from protobuf message <code>google.dataflow.v1beta3.CustomSourceLocation<\/code><\/p>\n<p>Extends <a href=\"https:\/\/github.com\/protocolbuffers\/protobuf-php\/tree\/v3.21.6\/src\/Google\/Protobuf\/Internal\/Message.php\" target=\"_blank\">Google\\Protobuf\\Internal\\Message<\/a><\/p>","examples":[],"resources":[],"methods":[{"id":"__construct","type":"constructor","name":"__construct","source":"Dataflow\/src\/V1beta3\/CustomSourceLocation.php#L35","description":"<p>Constructor.<\/p>","examples":[],"resources":[],"params":[{"name":"data","description":"<p>Optional. Data for populating the Message object.<\/p>","types":["<a href=\"http:\/\/php.net\/manual\/en\/language.types.array.php\" target=\"_blank\">array<\/a>"],"optional":false,"nullable":null},{"name":"data.stateful\n","description":"<p>Whether this source is stateful.<\/p>","types":["<a href=\"http:\/\/php.net\/manual\/en\/language.types.boolean.php\" target=\"_blank\">bool<\/a>"],"optional":null,"nullable":null}],"exceptions":[],"returns":[]},{"id":"getStateful","type":"instance","name":"getStateful","source":"Dataflow\/src\/V1beta3\/CustomSourceLocation.php#L46","description":"<p>Whether this source is stateful.<\/p>\n<p>Generated from protobuf field <code>bool stateful = 1;<\/code><\/p>","examples":[],"resources":[],"params":[],"exceptions":[],"returns":[{"types":["<a href=\"http:\/\/php.net\/manual\/en\/language.types.boolean.php\" target=\"_blank\">bool<\/a>"],"description":""}]},{"id":"setStateful","type":"instance","name":"setStateful","source":"Dataflow\/src\/V1beta3\/CustomSourceLocation.php#L58","description":"<p>Whether this source is stateful.<\/p>\n<p>Generated from protobuf field <code>bool stateful = 1;<\/code><\/p>","examples":[],"resources":[],"params":[{"name":"var","description":"<p>Whether this source is stateful.<\/p>\n","types":["<a href=\"http:\/\/php.net\/manual\/en\/language.types.boolean.php\" target=\"_blank\">bool<\/a>"],"optional":false,"nullable":null}],"exceptions":[],"returns":[{"types":["<a data-custom-type=\"dataflow\/v1beta3\/customsourcelocation\">Google\\Cloud\\Dataflow\\V1beta3\\CustomSourceLocation<\/a>"],"description":""}]}]}