{
    "schema": "1.0",
    "comment": "This file maps proto services\/RPCs to the corresponding library clients\/methods",
    "language": "php",
    "protoPackage": "google.cloud.vectorsearch.v1",
    "libraryPackage": "Google\\Cloud\\VectorSearch\\V1",
    "services": {
        "DataObjectSearchService": {
            "clients": {
                "grpc": {
                    "libraryClient": "DataObjectSearchServiceGapicClient",
                    "rpcs": {
                        "AggregateDataObjects": {
                            "methods": [
                                "aggregateDataObjects"
                            ]
                        },
                        "BatchSearchDataObjects": {
                            "methods": [
                                "batchSearchDataObjects"
                            ]
                        },
                        "QueryDataObjects": {
                            "methods": [
                                "queryDataObjects"
                            ]
                        },
                        "SearchDataObjects": {
                            "methods": [
                                "searchDataObjects"
                            ]
                        },
                        "GetLocation": {
                            "methods": [
                                "getLocation"
                            ]
                        },
                        "ListLocations": {
                            "methods": [
                                "listLocations"
                            ]
                        }
                    }
                }
            }
        },
        "DataObjectService": {
            "clients": {
                "grpc": {
                    "libraryClient": "DataObjectServiceGapicClient",
                    "rpcs": {
                        "BatchCreateDataObjects": {
                            "methods": [
                                "batchCreateDataObjects"
                            ]
                        },
                        "BatchDeleteDataObjects": {
                            "methods": [
                                "batchDeleteDataObjects"
                            ]
                        },
                        "BatchUpdateDataObjects": {
                            "methods": [
                                "batchUpdateDataObjects"
                            ]
                        },
                        "CreateDataObject": {
                            "methods": [
                                "createDataObject"
                            ]
                        },
                        "DeleteDataObject": {
                            "methods": [
                                "deleteDataObject"
                            ]
                        },
                        "GetDataObject": {
                            "methods": [
                                "getDataObject"
                            ]
                        },
                        "UpdateDataObject": {
                            "methods": [
                                "updateDataObject"
                            ]
                        },
                        "GetLocation": {
                            "methods": [
                                "getLocation"
                            ]
                        },
                        "ListLocations": {
                            "methods": [
                                "listLocations"
                            ]
                        }
                    }
                }
            }
        },
        "VectorSearchService": {
            "clients": {
                "grpc": {
                    "libraryClient": "VectorSearchServiceGapicClient",
                    "rpcs": {
                        "CreateCollection": {
                            "methods": [
                                "createCollection"
                            ]
                        },
                        "CreateIndex": {
                            "methods": [
                                "createIndex"
                            ]
                        },
                        "DeleteCollection": {
                            "methods": [
                                "deleteCollection"
                            ]
                        },
                        "DeleteIndex": {
                            "methods": [
                                "deleteIndex"
                            ]
                        },
                        "GetCollection": {
                            "methods": [
                                "getCollection"
                            ]
                        },
                        "GetIndex": {
                            "methods": [
                                "getIndex"
                            ]
                        },
                        "ImportDataObjects": {
                            "methods": [
                                "importDataObjects"
                            ]
                        },
                        "ListCollections": {
                            "methods": [
                                "listCollections"
                            ]
                        },
                        "ListIndexes": {
                            "methods": [
                                "listIndexes"
                            ]
                        },
                        "UpdateCollection": {
                            "methods": [
                                "updateCollection"
                            ]
                        },
                        "GetLocation": {
                            "methods": [
                                "getLocation"
                            ]
                        },
                        "ListLocations": {
                            "methods": [
                                "listLocations"
                            ]
                        }
                    }
                }
            }
        }
    }
}