{"id":"secretmanager\/v1\/gapic\/secretmanagerservicegapicclient","type":"","title":"Google\\Cloud\\SecretManager\\V1\\Gapic\\SecretManagerServiceGapicClient","name":"SecretManagerServiceGapicClient","description":"<p>Service Description: Secret Manager Service.<\/p>\n<p>Manages secrets and operations using those secrets. Implements a REST\nmodel with the following objects:<\/p>\n<ul>\n<li>[Secret][google.cloud.secretmanager.v1.Secret]<\/li>\n<li>[SecretVersion][google.cloud.secretmanager.v1.SecretVersion]<\/li>\n<\/ul>\n<p>This class provides the ability to make remote calls to the backing service through method\ncalls that map to API methods. Sample code to get started:<\/p>\n<pre><code>$secretManagerServiceClient = new SecretManagerServiceClient();\ntry {\n    $formattedParent = $secretManagerServiceClient-&gt;projectName('[PROJECT]');\n    \/\/ Iterate over pages of elements\n    $pagedResponse = $secretManagerServiceClient-&gt;listSecrets($formattedParent);\n    foreach ($pagedResponse-&gt;iteratePages() as $page) {\n        foreach ($page as $element) {\n            \/\/ doSomethingWith($element);\n        }\n    }\n\n    \/\/ Alternatively:\n\n    \/\/ Iterate through all elements\n    $pagedResponse = $secretManagerServiceClient-&gt;listSecrets($formattedParent);\n    foreach ($pagedResponse-&gt;iterateAllElements() as $element) {\n        \/\/ doSomethingWith($element);\n    }\n} finally {\n    $secretManagerServiceClient-&gt;close();\n}<\/code><\/pre>\n<p>Many parameters require resource names to be formatted in a particular way. To assist\nwith these names, this class includes a format method for each type of name, and additionally\na parseName method to extract the individual identifiers contained within formatted names\nthat are returned by the API.<\/p>","examples":[],"resources":[],"methods":[{"id":"projectName","type":"instance","name":"projectName","source":"SecretManager\/src\/V1\/Gapic\/SecretManagerServiceGapicClient.php#L207","description":"<p>Formats a string containing the fully-qualified path to represent\na project resource.<\/p>","examples":[],"resources":[],"params":[{"name":"project","description":"","types":["<a href=\"http:\/\/php.net\/manual\/en\/language.types.string.php\" target=\"_blank\">string<\/a>"],"optional":false,"nullable":null}],"exceptions":[],"returns":[{"types":["<a href=\"http:\/\/php.net\/manual\/en\/language.types.string.php\" target=\"_blank\">string<\/a>"],"description":"<p>The formatted project resource.<\/p>"}]},{"id":"secretName","type":"instance","name":"secretName","source":"SecretManager\/src\/V1\/Gapic\/SecretManagerServiceGapicClient.php#L223","description":"<p>Formats a string containing the fully-qualified path to represent\na secret resource.<\/p>","examples":[],"resources":[],"params":[{"name":"project","description":"","types":["<a href=\"http:\/\/php.net\/manual\/en\/language.types.string.php\" target=\"_blank\">string<\/a>"],"optional":false,"nullable":null},{"name":"secret","description":"","types":["<a href=\"http:\/\/php.net\/manual\/en\/language.types.string.php\" target=\"_blank\">string<\/a>"],"optional":false,"nullable":null}],"exceptions":[],"returns":[{"types":["<a href=\"http:\/\/php.net\/manual\/en\/language.types.string.php\" target=\"_blank\">string<\/a>"],"description":"<p>The formatted secret resource.<\/p>"}]},{"id":"secretVersionName","type":"instance","name":"secretVersionName","source":"SecretManager\/src\/V1\/Gapic\/SecretManagerServiceGapicClient.php#L241","description":"<p>Formats a string containing the fully-qualified path to represent\na secret_version resource.<\/p>","examples":[],"resources":[],"params":[{"name":"project","description":"","types":["<a href=\"http:\/\/php.net\/manual\/en\/language.types.string.php\" target=\"_blank\">string<\/a>"],"optional":false,"nullable":null},{"name":"secret","description":"","types":["<a href=\"http:\/\/php.net\/manual\/en\/language.types.string.php\" target=\"_blank\">string<\/a>"],"optional":false,"nullable":null},{"name":"secretVersion","description":"","types":["<a href=\"http:\/\/php.net\/manual\/en\/language.types.string.php\" target=\"_blank\">string<\/a>"],"optional":false,"nullable":null}],"exceptions":[],"returns":[{"types":["<a href=\"http:\/\/php.net\/manual\/en\/language.types.string.php\" target=\"_blank\">string<\/a>"],"description":"<p>The formatted secret_version resource.<\/p>"}]},{"id":"parseName","type":"instance","name":"parseName","source":"SecretManager\/src\/V1\/Gapic\/SecretManagerServiceGapicClient.php#L270","description":"<p>Parses a formatted name string and returns an associative array of the components in the name.<\/p>\n<p>The following name formats are supported:\nTemplate: Pattern<\/p>\n<ul>\n<li>project: projects\/{project}<\/li>\n<li>secret: projects\/{project}\/secrets\/{secret}<\/li>\n<li>secretVersion: projects\/{project}\/secrets\/{secret}\/versions\/{secret_version}.<\/li>\n<\/ul>\n<p>The optional $template argument can be supplied to specify a particular pattern, and must\nmatch one of the templates listed above. If no $template argument is provided, or if the\n$template argument does not match one of the templates listed, then parseName will check\neach of the supported templates, and return the first match.<\/p>","examples":[],"resources":[],"params":[{"name":"formattedName","description":"<p>The formatted name string<\/p>","types":["<a href=\"http:\/\/php.net\/manual\/en\/language.types.string.php\" target=\"_blank\">string<\/a>"],"optional":false,"nullable":null},{"name":"template","description":"<p>Optional name of template to match<\/p>","types":["<a href=\"http:\/\/php.net\/manual\/en\/language.types.string.php\" target=\"_blank\">string<\/a>"],"optional":false,"nullable":null}],"exceptions":[{"type":"\\Google\\ApiCore\\ValidationException","description":"If $formattedName could not be matched."}],"returns":[{"types":["<a href=\"http:\/\/php.net\/manual\/en\/language.types.array.php\" target=\"_blank\">array<\/a>"],"description":"<p>An associative array from name component IDs to component values.<\/p>"}]},{"id":"__construct","type":"constructor","name":"__construct","source":"SecretManager\/src\/V1\/Gapic\/SecretManagerServiceGapicClient.php#L346","description":"<p>Constructor.<\/p>","examples":[],"resources":[],"params":[{"name":"options","description":"<p>Optional. Options for configuring the service API wrapper.<\/p>","types":["<a href=\"http:\/\/php.net\/manual\/en\/language.types.array.php\" target=\"_blank\">array<\/a>"],"optional":false,"nullable":null},{"name":"options.serviceAddress\n","description":"<p><strong>Deprecated<\/strong>. This option will be removed in a future major release. Please utilize the <code>$apiEndpoint<\/code> option instead.<\/p>","types":["<a href=\"http:\/\/php.net\/manual\/en\/language.types.string.php\" target=\"_blank\">string<\/a>"],"optional":null,"nullable":null},{"name":"options.apiEndpoint\n","description":"<p>The address of the API remote host. May optionally include the port, formatted as &quot;<uri>:<port>&quot;. Default 'secretmanager.googleapis.com:443'.<\/p>","types":["<a href=\"http:\/\/php.net\/manual\/en\/language.types.string.php\" target=\"_blank\">string<\/a>"],"optional":null,"nullable":null},{"name":"options.credentials\n","description":"<p>The credentials to be used by the client to authorize API calls. This option accepts either a path to a credentials file, or a decoded credentials file as a PHP array. <em>Advanced usage<\/em>: In addition, this option can also accept a pre-constructed <a href=\"https:\/\/github.com\/googleapis\/google-auth-library-php\/tree\/v1.12.0\/src\/FetchAuthTokenInterface.php\" target=\"_blank\">Google\\Auth\\FetchAuthTokenInterface<\/a> object or <a href=\"https:\/\/googleapis.github.io\/gax-php\/1.3.1\/Google\/ApiCore\/CredentialsWrapper.html\" target=\"_blank\">Google\\ApiCore\\CredentialsWrapper<\/a> object. Note that when one of these objects are provided, any settings in $credentialsConfig will be ignored.<\/p>","types":["<a href=\"http:\/\/php.net\/manual\/en\/language.types.string.php\" target=\"_blank\">string<\/a>","<a href=\"http:\/\/php.net\/manual\/en\/language.types.array.php\" target=\"_blank\">array<\/a>","<a href=\"https:\/\/github.com\/googleapis\/google-auth-library-php\/tree\/v1.12.0\/src\/FetchAuthTokenInterface.php\" target=\"_blank\">Google\\Auth\\FetchAuthTokenInterface<\/a>","<a href=\"https:\/\/googleapis.github.io\/gax-php\/1.3.1\/Google\/ApiCore\/CredentialsWrapper.html\" target=\"_blank\">Google\\ApiCore\\CredentialsWrapper<\/a>"],"optional":null,"nullable":null},{"name":"options.credentialsConfig\n","description":"<p>Options used to configure credentials, including auth token caching, for the client. For a full list of supporting configuration options, see <a href=\"https:\/\/googleapis.github.io\/gax-php\/1.3.1\/Google\/ApiCore\/CredentialsWrapper.html\" target=\"_blank\">Google\\ApiCore\\CredentialsWrapper::build()<\/a>.<\/p>","types":["<a href=\"http:\/\/php.net\/manual\/en\/language.types.array.php\" target=\"_blank\">array<\/a>"],"optional":null,"nullable":null},{"name":"options.disableRetries\n","description":"<p>Determines whether or not retries defined by the client configuration should be disabled. Defaults to <code>false<\/code>.<\/p>","types":["<a href=\"http:\/\/php.net\/manual\/en\/language.types.boolean.php\" target=\"_blank\">bool<\/a>"],"optional":null,"nullable":null},{"name":"options.clientConfig\n","description":"<p>Client method configuration, including retry settings. This option can be either a path to a JSON file, or a PHP array containing the decoded JSON data. By default this settings points to the default client config file, which is provided in the resources folder.<\/p>","types":["<a href=\"http:\/\/php.net\/manual\/en\/language.types.string.php\" target=\"_blank\">string<\/a>","<a href=\"http:\/\/php.net\/manual\/en\/language.types.array.php\" target=\"_blank\">array<\/a>"],"optional":null,"nullable":null},{"name":"options.transport\n","description":"<p>The transport used for executing network requests. May be either the string <code>rest<\/code> or <code>grpc<\/code>. Defaults to <code>grpc<\/code> if gRPC support is detected on the system. <em>Advanced usage<\/em>: Additionally, it is possible to pass in an already instantiated <a href=\"https:\/\/googleapis.github.io\/gax-php\/1.3.1\/Google\/ApiCore\/Transport\/TransportInterface.html\" target=\"_blank\">Google\\ApiCore\\Transport\\TransportInterface<\/a> object. Note that when this object is provided, any settings in $transportConfig, and any <code>$apiEndpoint<\/code> setting, will be ignored.<\/p>","types":["<a href=\"http:\/\/php.net\/manual\/en\/language.types.string.php\" target=\"_blank\">string<\/a>","<a href=\"https:\/\/googleapis.github.io\/gax-php\/1.3.1\/Google\/ApiCore\/Transport\/TransportInterface.html\" target=\"_blank\">Google\\ApiCore\\Transport\\TransportInterface<\/a>"],"optional":null,"nullable":null},{"name":"options.transportConfig\n","description":"<p>Configuration options that will be used to construct the transport. Options for each supported transport type should be passed in a key for that transport. For example: $transportConfig = [ 'grpc' =&gt; [...], 'rest' =&gt; [...] ]; See the <a href=\"https:\/\/googleapis.github.io\/gax-php\/1.3.1\/Google\/ApiCore\/Transport\/GrpcTransport.html\" target=\"_blank\">Google\\ApiCore\\Transport\\GrpcTransport::build()<\/a> and <a href=\"https:\/\/googleapis.github.io\/gax-php\/1.3.1\/Google\/ApiCore\/Transport\/RestTransport.html\" target=\"_blank\">Google\\ApiCore\\Transport\\RestTransport::build()<\/a> methods for the supported options.<\/p>","types":["<a href=\"http:\/\/php.net\/manual\/en\/language.types.array.php\" target=\"_blank\">array<\/a>"],"optional":null,"nullable":null}],"exceptions":[{"type":"\\Google\\ApiCore\\ValidationException","description":""}],"returns":[]},{"id":"listSecrets","type":"instance","name":"listSecrets","source":"SecretManager\/src\/V1\/Gapic\/SecretManagerServiceGapicClient.php#L406","description":"<p>Lists [Secrets][google.cloud.secretmanager.v1.Secret].<\/p>\n<p>Sample code:<\/p>\n<pre><code>$secretManagerServiceClient = new SecretManagerServiceClient();\ntry {\n    $formattedParent = $secretManagerServiceClient-&gt;projectName('[PROJECT]');\n    \/\/ Iterate over pages of elements\n    $pagedResponse = $secretManagerServiceClient-&gt;listSecrets($formattedParent);\n    foreach ($pagedResponse-&gt;iteratePages() as $page) {\n        foreach ($page as $element) {\n            \/\/ doSomethingWith($element);\n        }\n    }\n\n    \/\/ Alternatively:\n\n    \/\/ Iterate through all elements\n    $pagedResponse = $secretManagerServiceClient-&gt;listSecrets($formattedParent);\n    foreach ($pagedResponse-&gt;iterateAllElements() as $element) {\n        \/\/ doSomethingWith($element);\n    }\n} finally {\n    $secretManagerServiceClient-&gt;close();\n}<\/code><\/pre>","examples":[],"resources":[],"params":[{"name":"parent","description":"<p>Required. The resource name of the project associated with the\n[Secrets][google.cloud.secretmanager.v1.Secret], in the format <code>projects\/*<\/code>.<\/p>","types":["<a href=\"http:\/\/php.net\/manual\/en\/language.types.string.php\" target=\"_blank\">string<\/a>"],"optional":false,"nullable":null},{"name":"optionalArgs","description":"<p>Optional.<\/p>","types":["<a href=\"http:\/\/php.net\/manual\/en\/language.types.array.php\" target=\"_blank\">array<\/a>"],"optional":false,"nullable":null},{"name":"optionalArgs.pageSize\n","description":"<p>The maximum number of resources contained in the underlying API response. The API may return fewer values in a page, even if there are additional values to be retrieved.<\/p>","types":["<a href=\"http:\/\/php.net\/manual\/en\/language.types.integer.php\" target=\"_blank\">int<\/a>"],"optional":null,"nullable":null},{"name":"optionalArgs.pageToken\n","description":"<p>A page token is used to specify a page of values to be returned. If no page token is specified (the default), the first page of values will be returned. Any page token used here must have been generated by a previous call to the API.<\/p>","types":["<a href=\"http:\/\/php.net\/manual\/en\/language.types.string.php\" target=\"_blank\">string<\/a>"],"optional":null,"nullable":null},{"name":"optionalArgs.retrySettings\n","description":"<p>Retry settings to use for this call. Can be a <a href=\"https:\/\/googleapis.github.io\/gax-php\/1.3.1\/Google\/ApiCore\/RetrySettings.html\" target=\"_blank\">Google\\ApiCore\\RetrySettings<\/a> object, or an associative array of retry settings parameters. See the documentation on <a href=\"https:\/\/googleapis.github.io\/gax-php\/1.3.1\/Google\/ApiCore\/RetrySettings.html\" target=\"_blank\">Google\\ApiCore\\RetrySettings<\/a> for example usage.<\/p>","types":["<a href=\"https:\/\/googleapis.github.io\/gax-php\/1.3.1\/Google\/ApiCore\/RetrySettings.html\" target=\"_blank\">Google\\ApiCore\\RetrySettings<\/a>","<a href=\"http:\/\/php.net\/manual\/en\/language.types.array.php\" target=\"_blank\">array<\/a>"],"optional":null,"nullable":null}],"exceptions":[{"type":"\\Google\\ApiCore\\ApiException","description":"if the remote call fails"}],"returns":[{"types":["<a href=\"https:\/\/googleapis.github.io\/gax-php\/1.3.1\/Google\/ApiCore\/PagedListResponse.html\" target=\"_blank\">Google\\ApiCore\\PagedListResponse<\/a>"],"description":""}]},{"id":"createSecret","type":"instance","name":"createSecret","source":"SecretManager\/src\/V1\/Gapic\/SecretManagerServiceGapicClient.php#L470","description":"<p>Creates a new [Secret][google.cloud.secretmanager.v1.Secret] containing no [SecretVersions][google.cloud.secretmanager.v1.SecretVersion].<\/p>\n<p>Sample code:<\/p>\n<pre><code>$secretManagerServiceClient = new SecretManagerServiceClient();\ntry {\n    $formattedParent = $secretManagerServiceClient-&gt;projectName('[PROJECT]');\n    $secretId = '';\n    $secret = new Secret();\n    $response = $secretManagerServiceClient-&gt;createSecret($formattedParent, $secretId, $secret);\n} finally {\n    $secretManagerServiceClient-&gt;close();\n}<\/code><\/pre>","examples":[],"resources":[],"params":[{"name":"parent","description":"<p>Required. The resource name of the project to associate with the\n[Secret][google.cloud.secretmanager.v1.Secret], in the format <code>projects\/*<\/code>.<\/p>","types":["<a href=\"http:\/\/php.net\/manual\/en\/language.types.string.php\" target=\"_blank\">string<\/a>"],"optional":false,"nullable":null},{"name":"secretId","description":"<p>Required. This must be unique within the project.<\/p>\n<p>A secret ID is a string with a maximum length of 255 characters and can\ncontain uppercase and lowercase letters, numerals, and the hyphen (<code>-<\/code>) and\nunderscore (<code>_<\/code>) characters.<\/p>","types":["<a href=\"http:\/\/php.net\/manual\/en\/language.types.string.php\" target=\"_blank\">string<\/a>"],"optional":false,"nullable":null},{"name":"secret","description":"<p>Required. A [Secret][google.cloud.secretmanager.v1.Secret] with initial field values.<\/p>","types":["<a data-custom-type=\"secretmanager\/v1\/secret\">Google\\Cloud\\SecretManager\\V1\\Secret<\/a>"],"optional":false,"nullable":null},{"name":"optionalArgs","description":"<p>Optional.<\/p>","types":["<a href=\"http:\/\/php.net\/manual\/en\/language.types.array.php\" target=\"_blank\">array<\/a>"],"optional":false,"nullable":null},{"name":"optionalArgs.retrySettings\n","description":"<p>Retry settings to use for this call. Can be a <a href=\"https:\/\/googleapis.github.io\/gax-php\/1.3.1\/Google\/ApiCore\/RetrySettings.html\" target=\"_blank\">Google\\ApiCore\\RetrySettings<\/a> object, or an associative array of retry settings parameters. See the documentation on <a href=\"https:\/\/googleapis.github.io\/gax-php\/1.3.1\/Google\/ApiCore\/RetrySettings.html\" target=\"_blank\">Google\\ApiCore\\RetrySettings<\/a> for example usage.<\/p>","types":["<a href=\"https:\/\/googleapis.github.io\/gax-php\/1.3.1\/Google\/ApiCore\/RetrySettings.html\" target=\"_blank\">Google\\ApiCore\\RetrySettings<\/a>","<a href=\"http:\/\/php.net\/manual\/en\/language.types.array.php\" target=\"_blank\">array<\/a>"],"optional":null,"nullable":null}],"exceptions":[{"type":"\\Google\\ApiCore\\ApiException","description":"if the remote call fails"}],"returns":[{"types":["<a data-custom-type=\"secretmanager\/v1\/secret\">Google\\Cloud\\SecretManager\\V1\\Secret<\/a>"],"description":""}]},{"id":"addSecretVersion","type":"instance","name":"addSecretVersion","source":"SecretManager\/src\/V1\/Gapic\/SecretManagerServiceGapicClient.php#L525","description":"<p>Creates a new [SecretVersion][google.cloud.secretmanager.v1.SecretVersion] containing secret data and attaches\nit to an existing [Secret][google.cloud.secretmanager.v1.Secret].<\/p>\n<p>Sample code:<\/p>\n<pre><code>$secretManagerServiceClient = new SecretManagerServiceClient();\ntry {\n    $formattedParent = $secretManagerServiceClient-&gt;secretName('[PROJECT]', '[SECRET]');\n    $payload = new SecretPayload();\n    $response = $secretManagerServiceClient-&gt;addSecretVersion($formattedParent, $payload);\n} finally {\n    $secretManagerServiceClient-&gt;close();\n}<\/code><\/pre>","examples":[],"resources":[],"params":[{"name":"parent","description":"<p>Required. The resource name of the [Secret][google.cloud.secretmanager.v1.Secret] to associate with the\n[SecretVersion][google.cloud.secretmanager.v1.SecretVersion] in the format <code>projects\/&amp;#42;\/secrets\/*<\/code>.<\/p>","types":["<a href=\"http:\/\/php.net\/manual\/en\/language.types.string.php\" target=\"_blank\">string<\/a>"],"optional":false,"nullable":null},{"name":"payload","description":"<p>Required. The secret payload of the [SecretVersion][google.cloud.secretmanager.v1.SecretVersion].<\/p>","types":["<a data-custom-type=\"secretmanager\/v1\/secretpayload\">Google\\Cloud\\SecretManager\\V1\\SecretPayload<\/a>"],"optional":false,"nullable":null},{"name":"optionalArgs","description":"<p>Optional.<\/p>","types":["<a href=\"http:\/\/php.net\/manual\/en\/language.types.array.php\" target=\"_blank\">array<\/a>"],"optional":false,"nullable":null},{"name":"optionalArgs.retrySettings\n","description":"<p>Retry settings to use for this call. Can be a <a href=\"https:\/\/googleapis.github.io\/gax-php\/1.3.1\/Google\/ApiCore\/RetrySettings.html\" target=\"_blank\">Google\\ApiCore\\RetrySettings<\/a> object, or an associative array of retry settings parameters. See the documentation on <a href=\"https:\/\/googleapis.github.io\/gax-php\/1.3.1\/Google\/ApiCore\/RetrySettings.html\" target=\"_blank\">Google\\ApiCore\\RetrySettings<\/a> for example usage.<\/p>","types":["<a href=\"https:\/\/googleapis.github.io\/gax-php\/1.3.1\/Google\/ApiCore\/RetrySettings.html\" target=\"_blank\">Google\\ApiCore\\RetrySettings<\/a>","<a href=\"http:\/\/php.net\/manual\/en\/language.types.array.php\" target=\"_blank\">array<\/a>"],"optional":null,"nullable":null}],"exceptions":[{"type":"\\Google\\ApiCore\\ApiException","description":"if the remote call fails"}],"returns":[{"types":["<a data-custom-type=\"secretmanager\/v1\/secretversion\">Google\\Cloud\\SecretManager\\V1\\SecretVersion<\/a>"],"description":""}]},{"id":"getSecret","type":"instance","name":"getSecret","source":"SecretManager\/src\/V1\/Gapic\/SecretManagerServiceGapicClient.php#L575","description":"<p>Gets metadata for a given [Secret][google.cloud.secretmanager.v1.Secret].<\/p>\n<p>Sample code:<\/p>\n<pre><code>$secretManagerServiceClient = new SecretManagerServiceClient();\ntry {\n    $formattedName = $secretManagerServiceClient-&gt;secretName('[PROJECT]', '[SECRET]');\n    $response = $secretManagerServiceClient-&gt;getSecret($formattedName);\n} finally {\n    $secretManagerServiceClient-&gt;close();\n}<\/code><\/pre>","examples":[],"resources":[],"params":[{"name":"name","description":"<p>Required. The resource name of the [Secret][google.cloud.secretmanager.v1.Secret], in the format <code>projects\/&amp;#42;\/secrets\/*<\/code>.<\/p>","types":["<a href=\"http:\/\/php.net\/manual\/en\/language.types.string.php\" target=\"_blank\">string<\/a>"],"optional":false,"nullable":null},{"name":"optionalArgs","description":"<p>Optional.<\/p>","types":["<a href=\"http:\/\/php.net\/manual\/en\/language.types.array.php\" target=\"_blank\">array<\/a>"],"optional":false,"nullable":null},{"name":"optionalArgs.retrySettings\n","description":"<p>Retry settings to use for this call. Can be a <a href=\"https:\/\/googleapis.github.io\/gax-php\/1.3.1\/Google\/ApiCore\/RetrySettings.html\" target=\"_blank\">Google\\ApiCore\\RetrySettings<\/a> object, or an associative array of retry settings parameters. See the documentation on <a href=\"https:\/\/googleapis.github.io\/gax-php\/1.3.1\/Google\/ApiCore\/RetrySettings.html\" target=\"_blank\">Google\\ApiCore\\RetrySettings<\/a> for example usage.<\/p>","types":["<a href=\"https:\/\/googleapis.github.io\/gax-php\/1.3.1\/Google\/ApiCore\/RetrySettings.html\" target=\"_blank\">Google\\ApiCore\\RetrySettings<\/a>","<a href=\"http:\/\/php.net\/manual\/en\/language.types.array.php\" target=\"_blank\">array<\/a>"],"optional":null,"nullable":null}],"exceptions":[{"type":"\\Google\\ApiCore\\ApiException","description":"if the remote call fails"}],"returns":[{"types":["<a data-custom-type=\"secretmanager\/v1\/secret\">Google\\Cloud\\SecretManager\\V1\\Secret<\/a>"],"description":""}]},{"id":"updateSecret","type":"instance","name":"updateSecret","source":"SecretManager\/src\/V1\/Gapic\/SecretManagerServiceGapicClient.php#L626","description":"<p>Updates metadata of an existing [Secret][google.cloud.secretmanager.v1.Secret].<\/p>\n<p>Sample code:<\/p>\n<pre><code>$secretManagerServiceClient = new SecretManagerServiceClient();\ntry {\n    $secret = new Secret();\n    $updateMask = new FieldMask();\n    $response = $secretManagerServiceClient-&gt;updateSecret($secret, $updateMask);\n} finally {\n    $secretManagerServiceClient-&gt;close();\n}<\/code><\/pre>","examples":[],"resources":[],"params":[{"name":"secret","description":"<p>Required. [Secret][google.cloud.secretmanager.v1.Secret] with updated field values.<\/p>","types":["<a data-custom-type=\"secretmanager\/v1\/secret\">Google\\Cloud\\SecretManager\\V1\\Secret<\/a>"],"optional":false,"nullable":null},{"name":"updateMask","description":"<p>Required. Specifies the fields to be updated.<\/p>","types":["<a href=\"https:\/\/github.com\/protocolbuffers\/protobuf-php\/tree\/v3.13.0\/src\/Google\/Protobuf\/FieldMask.php\" target=\"_blank\">Google\\Protobuf\\FieldMask<\/a>"],"optional":false,"nullable":null},{"name":"optionalArgs","description":"<p>Optional.<\/p>","types":["<a href=\"http:\/\/php.net\/manual\/en\/language.types.array.php\" target=\"_blank\">array<\/a>"],"optional":false,"nullable":null},{"name":"optionalArgs.retrySettings\n","description":"<p>Retry settings to use for this call. Can be a <a href=\"https:\/\/googleapis.github.io\/gax-php\/1.3.1\/Google\/ApiCore\/RetrySettings.html\" target=\"_blank\">Google\\ApiCore\\RetrySettings<\/a> object, or an associative array of retry settings parameters. See the documentation on <a href=\"https:\/\/googleapis.github.io\/gax-php\/1.3.1\/Google\/ApiCore\/RetrySettings.html\" target=\"_blank\">Google\\ApiCore\\RetrySettings<\/a> for example usage.<\/p>","types":["<a href=\"https:\/\/googleapis.github.io\/gax-php\/1.3.1\/Google\/ApiCore\/RetrySettings.html\" target=\"_blank\">Google\\ApiCore\\RetrySettings<\/a>","<a href=\"http:\/\/php.net\/manual\/en\/language.types.array.php\" target=\"_blank\">array<\/a>"],"optional":null,"nullable":null}],"exceptions":[{"type":"\\Google\\ApiCore\\ApiException","description":"if the remote call fails"}],"returns":[{"types":["<a data-custom-type=\"secretmanager\/v1\/secret\">Google\\Cloud\\SecretManager\\V1\\Secret<\/a>"],"description":""}]},{"id":"deleteSecret","type":"instance","name":"deleteSecret","source":"SecretManager\/src\/V1\/Gapic\/SecretManagerServiceGapicClient.php#L675","description":"<p>Deletes a [Secret][google.cloud.secretmanager.v1.Secret].<\/p>\n<p>Sample code:<\/p>\n<pre><code>$secretManagerServiceClient = new SecretManagerServiceClient();\ntry {\n    $formattedName = $secretManagerServiceClient-&gt;secretName('[PROJECT]', '[SECRET]');\n    $secretManagerServiceClient-&gt;deleteSecret($formattedName);\n} finally {\n    $secretManagerServiceClient-&gt;close();\n}<\/code><\/pre>","examples":[],"resources":[],"params":[{"name":"name","description":"<p>Required. The resource name of the [Secret][google.cloud.secretmanager.v1.Secret] to delete in the format\n<code>projects\/&amp;#42;\/secrets\/*<\/code>.<\/p>","types":["<a href=\"http:\/\/php.net\/manual\/en\/language.types.string.php\" target=\"_blank\">string<\/a>"],"optional":false,"nullable":null},{"name":"optionalArgs","description":"<p>Optional.<\/p>","types":["<a href=\"http:\/\/php.net\/manual\/en\/language.types.array.php\" target=\"_blank\">array<\/a>"],"optional":false,"nullable":null},{"name":"optionalArgs.retrySettings\n","description":"<p>Retry settings to use for this call. Can be a <a href=\"https:\/\/googleapis.github.io\/gax-php\/1.3.1\/Google\/ApiCore\/RetrySettings.html\" target=\"_blank\">Google\\ApiCore\\RetrySettings<\/a> object, or an associative array of retry settings parameters. See the documentation on <a href=\"https:\/\/googleapis.github.io\/gax-php\/1.3.1\/Google\/ApiCore\/RetrySettings.html\" target=\"_blank\">Google\\ApiCore\\RetrySettings<\/a> for example usage.<\/p>","types":["<a href=\"https:\/\/googleapis.github.io\/gax-php\/1.3.1\/Google\/ApiCore\/RetrySettings.html\" target=\"_blank\">Google\\ApiCore\\RetrySettings<\/a>","<a href=\"http:\/\/php.net\/manual\/en\/language.types.array.php\" target=\"_blank\">array<\/a>"],"optional":null,"nullable":null}],"exceptions":[{"type":"\\Google\\ApiCore\\ApiException","description":"if the remote call fails"}],"returns":[]},{"id":"listSecretVersions","type":"instance","name":"listSecretVersions","source":"SecretManager\/src\/V1\/Gapic\/SecretManagerServiceGapicClient.php#L751","description":"<p>Lists [SecretVersions][google.cloud.secretmanager.v1.SecretVersion]. This call does not return secret\ndata.<\/p>\n<p>Sample code:<\/p>\n<pre><code>$secretManagerServiceClient = new SecretManagerServiceClient();\ntry {\n    $formattedParent = $secretManagerServiceClient-&gt;secretName('[PROJECT]', '[SECRET]');\n    \/\/ Iterate over pages of elements\n    $pagedResponse = $secretManagerServiceClient-&gt;listSecretVersions($formattedParent);\n    foreach ($pagedResponse-&gt;iteratePages() as $page) {\n        foreach ($page as $element) {\n            \/\/ doSomethingWith($element);\n        }\n    }\n\n    \/\/ Alternatively:\n\n    \/\/ Iterate through all elements\n    $pagedResponse = $secretManagerServiceClient-&gt;listSecretVersions($formattedParent);\n    foreach ($pagedResponse-&gt;iterateAllElements() as $element) {\n        \/\/ doSomethingWith($element);\n    }\n} finally {\n    $secretManagerServiceClient-&gt;close();\n}<\/code><\/pre>","examples":[],"resources":[],"params":[{"name":"parent","description":"<p>Required. The resource name of the [Secret][google.cloud.secretmanager.v1.Secret] associated with the\n[SecretVersions][google.cloud.secretmanager.v1.SecretVersion] to list, in the format\n<code>projects\/&amp;#42;\/secrets\/*<\/code>.<\/p>","types":["<a href=\"http:\/\/php.net\/manual\/en\/language.types.string.php\" target=\"_blank\">string<\/a>"],"optional":false,"nullable":null},{"name":"optionalArgs","description":"<p>Optional.<\/p>","types":["<a href=\"http:\/\/php.net\/manual\/en\/language.types.array.php\" target=\"_blank\">array<\/a>"],"optional":false,"nullable":null},{"name":"optionalArgs.pageSize\n","description":"<p>The maximum number of resources contained in the underlying API response. The API may return fewer values in a page, even if there are additional values to be retrieved.<\/p>","types":["<a href=\"http:\/\/php.net\/manual\/en\/language.types.integer.php\" target=\"_blank\">int<\/a>"],"optional":null,"nullable":null},{"name":"optionalArgs.pageToken\n","description":"<p>A page token is used to specify a page of values to be returned. If no page token is specified (the default), the first page of values will be returned. Any page token used here must have been generated by a previous call to the API.<\/p>","types":["<a href=\"http:\/\/php.net\/manual\/en\/language.types.string.php\" target=\"_blank\">string<\/a>"],"optional":null,"nullable":null},{"name":"optionalArgs.retrySettings\n","description":"<p>Retry settings to use for this call. Can be a <a href=\"https:\/\/googleapis.github.io\/gax-php\/1.3.1\/Google\/ApiCore\/RetrySettings.html\" target=\"_blank\">Google\\ApiCore\\RetrySettings<\/a> object, or an associative array of retry settings parameters. See the documentation on <a href=\"https:\/\/googleapis.github.io\/gax-php\/1.3.1\/Google\/ApiCore\/RetrySettings.html\" target=\"_blank\">Google\\ApiCore\\RetrySettings<\/a> for example usage.<\/p>","types":["<a href=\"https:\/\/googleapis.github.io\/gax-php\/1.3.1\/Google\/ApiCore\/RetrySettings.html\" target=\"_blank\">Google\\ApiCore\\RetrySettings<\/a>","<a href=\"http:\/\/php.net\/manual\/en\/language.types.array.php\" target=\"_blank\">array<\/a>"],"optional":null,"nullable":null}],"exceptions":[{"type":"\\Google\\ApiCore\\ApiException","description":"if the remote call fails"}],"returns":[{"types":["<a href=\"https:\/\/googleapis.github.io\/gax-php\/1.3.1\/Google\/ApiCore\/PagedListResponse.html\" target=\"_blank\">Google\\ApiCore\\PagedListResponse<\/a>"],"description":""}]},{"id":"getSecretVersion","type":"instance","name":"getSecretVersion","source":"SecretManager\/src\/V1\/Gapic\/SecretManagerServiceGapicClient.php#L812","description":"<p>Gets metadata for a [SecretVersion][google.cloud.secretmanager.v1.SecretVersion].<\/p>\n<p><code>projects\/&amp;#42;\/secrets\/&amp;#42;\/versions\/latest<\/code> is an alias to the <code>latest<\/code>\n[SecretVersion][google.cloud.secretmanager.v1.SecretVersion].<\/p>\n<p>Sample code:<\/p>\n<pre><code>$secretManagerServiceClient = new SecretManagerServiceClient();\ntry {\n    $formattedName = $secretManagerServiceClient-&gt;secretVersionName('[PROJECT]', '[SECRET]', '[SECRET_VERSION]');\n    $response = $secretManagerServiceClient-&gt;getSecretVersion($formattedName);\n} finally {\n    $secretManagerServiceClient-&gt;close();\n}<\/code><\/pre>","examples":[],"resources":[],"params":[{"name":"name","description":"<p>Required. The resource name of the [SecretVersion][google.cloud.secretmanager.v1.SecretVersion] in the format\n<code>projects\/&amp;#42;\/secrets\/&amp;#42;\/versions\/*<\/code>.\n<code>projects\/&amp;#42;\/secrets\/&amp;#42;\/versions\/latest<\/code> is an alias to the <code>latest<\/code>\n[SecretVersion][google.cloud.secretmanager.v1.SecretVersion].<\/p>","types":["<a href=\"http:\/\/php.net\/manual\/en\/language.types.string.php\" target=\"_blank\">string<\/a>"],"optional":false,"nullable":null},{"name":"optionalArgs","description":"<p>Optional.<\/p>","types":["<a href=\"http:\/\/php.net\/manual\/en\/language.types.array.php\" target=\"_blank\">array<\/a>"],"optional":false,"nullable":null},{"name":"optionalArgs.retrySettings\n","description":"<p>Retry settings to use for this call. Can be a <a href=\"https:\/\/googleapis.github.io\/gax-php\/1.3.1\/Google\/ApiCore\/RetrySettings.html\" target=\"_blank\">Google\\ApiCore\\RetrySettings<\/a> object, or an associative array of retry settings parameters. See the documentation on <a href=\"https:\/\/googleapis.github.io\/gax-php\/1.3.1\/Google\/ApiCore\/RetrySettings.html\" target=\"_blank\">Google\\ApiCore\\RetrySettings<\/a> for example usage.<\/p>","types":["<a href=\"https:\/\/googleapis.github.io\/gax-php\/1.3.1\/Google\/ApiCore\/RetrySettings.html\" target=\"_blank\">Google\\ApiCore\\RetrySettings<\/a>","<a href=\"http:\/\/php.net\/manual\/en\/language.types.array.php\" target=\"_blank\">array<\/a>"],"optional":null,"nullable":null}],"exceptions":[{"type":"\\Google\\ApiCore\\ApiException","description":"if the remote call fails"}],"returns":[{"types":["<a data-custom-type=\"secretmanager\/v1\/secretversion\">Google\\Cloud\\SecretManager\\V1\\SecretVersion<\/a>"],"description":""}]},{"id":"accessSecretVersion","type":"instance","name":"accessSecretVersion","source":"SecretManager\/src\/V1\/Gapic\/SecretManagerServiceGapicClient.php#L865","description":"<p>Accesses a [SecretVersion][google.cloud.secretmanager.v1.SecretVersion]. This call returns the secret data.<\/p>\n<p><code>projects\/&amp;#42;\/secrets\/&amp;#42;\/versions\/latest<\/code> is an alias to the <code>latest<\/code>\n[SecretVersion][google.cloud.secretmanager.v1.SecretVersion].<\/p>\n<p>Sample code:<\/p>\n<pre><code>$secretManagerServiceClient = new SecretManagerServiceClient();\ntry {\n    $formattedName = $secretManagerServiceClient-&gt;secretVersionName('[PROJECT]', '[SECRET]', '[SECRET_VERSION]');\n    $response = $secretManagerServiceClient-&gt;accessSecretVersion($formattedName);\n} finally {\n    $secretManagerServiceClient-&gt;close();\n}<\/code><\/pre>","examples":[],"resources":[],"params":[{"name":"name","description":"<p>Required. The resource name of the [SecretVersion][google.cloud.secretmanager.v1.SecretVersion] in the format\n<code>projects\/&amp;#42;\/secrets\/&amp;#42;\/versions\/*<\/code>.<\/p>","types":["<a href=\"http:\/\/php.net\/manual\/en\/language.types.string.php\" target=\"_blank\">string<\/a>"],"optional":false,"nullable":null},{"name":"optionalArgs","description":"<p>Optional.<\/p>","types":["<a href=\"http:\/\/php.net\/manual\/en\/language.types.array.php\" target=\"_blank\">array<\/a>"],"optional":false,"nullable":null},{"name":"optionalArgs.retrySettings\n","description":"<p>Retry settings to use for this call. Can be a <a href=\"https:\/\/googleapis.github.io\/gax-php\/1.3.1\/Google\/ApiCore\/RetrySettings.html\" target=\"_blank\">Google\\ApiCore\\RetrySettings<\/a> object, or an associative array of retry settings parameters. See the documentation on <a href=\"https:\/\/googleapis.github.io\/gax-php\/1.3.1\/Google\/ApiCore\/RetrySettings.html\" target=\"_blank\">Google\\ApiCore\\RetrySettings<\/a> for example usage.<\/p>","types":["<a href=\"https:\/\/googleapis.github.io\/gax-php\/1.3.1\/Google\/ApiCore\/RetrySettings.html\" target=\"_blank\">Google\\ApiCore\\RetrySettings<\/a>","<a href=\"http:\/\/php.net\/manual\/en\/language.types.array.php\" target=\"_blank\">array<\/a>"],"optional":null,"nullable":null}],"exceptions":[{"type":"\\Google\\ApiCore\\ApiException","description":"if the remote call fails"}],"returns":[{"types":["<a data-custom-type=\"secretmanager\/v1\/accesssecretversionresponse\">Google\\Cloud\\SecretManager\\V1\\AccessSecretVersionResponse<\/a>"],"description":""}]},{"id":"disableSecretVersion","type":"instance","name":"disableSecretVersion","source":"SecretManager\/src\/V1\/Gapic\/SecretManagerServiceGapicClient.php#L918","description":"<p>Disables a [SecretVersion][google.cloud.secretmanager.v1.SecretVersion].<\/p>\n<p>Sets the [state][google.cloud.secretmanager.v1.SecretVersion.state] of the [SecretVersion][google.cloud.secretmanager.v1.SecretVersion] to\n[DISABLED][google.cloud.secretmanager.v1.SecretVersion.State.DISABLED].<\/p>\n<p>Sample code:<\/p>\n<pre><code>$secretManagerServiceClient = new SecretManagerServiceClient();\ntry {\n    $formattedName = $secretManagerServiceClient-&gt;secretVersionName('[PROJECT]', '[SECRET]', '[SECRET_VERSION]');\n    $response = $secretManagerServiceClient-&gt;disableSecretVersion($formattedName);\n} finally {\n    $secretManagerServiceClient-&gt;close();\n}<\/code><\/pre>","examples":[],"resources":[],"params":[{"name":"name","description":"<p>Required. The resource name of the [SecretVersion][google.cloud.secretmanager.v1.SecretVersion] to disable in the format\n<code>projects\/&amp;#42;\/secrets\/&amp;#42;\/versions\/*<\/code>.<\/p>","types":["<a href=\"http:\/\/php.net\/manual\/en\/language.types.string.php\" target=\"_blank\">string<\/a>"],"optional":false,"nullable":null},{"name":"optionalArgs","description":"<p>Optional.<\/p>","types":["<a href=\"http:\/\/php.net\/manual\/en\/language.types.array.php\" target=\"_blank\">array<\/a>"],"optional":false,"nullable":null},{"name":"optionalArgs.retrySettings\n","description":"<p>Retry settings to use for this call. Can be a <a href=\"https:\/\/googleapis.github.io\/gax-php\/1.3.1\/Google\/ApiCore\/RetrySettings.html\" target=\"_blank\">Google\\ApiCore\\RetrySettings<\/a> object, or an associative array of retry settings parameters. See the documentation on <a href=\"https:\/\/googleapis.github.io\/gax-php\/1.3.1\/Google\/ApiCore\/RetrySettings.html\" target=\"_blank\">Google\\ApiCore\\RetrySettings<\/a> for example usage.<\/p>","types":["<a href=\"https:\/\/googleapis.github.io\/gax-php\/1.3.1\/Google\/ApiCore\/RetrySettings.html\" target=\"_blank\">Google\\ApiCore\\RetrySettings<\/a>","<a href=\"http:\/\/php.net\/manual\/en\/language.types.array.php\" target=\"_blank\">array<\/a>"],"optional":null,"nullable":null}],"exceptions":[{"type":"\\Google\\ApiCore\\ApiException","description":"if the remote call fails"}],"returns":[{"types":["<a data-custom-type=\"secretmanager\/v1\/secretversion\">Google\\Cloud\\SecretManager\\V1\\SecretVersion<\/a>"],"description":""}]},{"id":"enableSecretVersion","type":"instance","name":"enableSecretVersion","source":"SecretManager\/src\/V1\/Gapic\/SecretManagerServiceGapicClient.php#L971","description":"<p>Enables a [SecretVersion][google.cloud.secretmanager.v1.SecretVersion].<\/p>\n<p>Sets the [state][google.cloud.secretmanager.v1.SecretVersion.state] of the [SecretVersion][google.cloud.secretmanager.v1.SecretVersion] to\n[ENABLED][google.cloud.secretmanager.v1.SecretVersion.State.ENABLED].<\/p>\n<p>Sample code:<\/p>\n<pre><code>$secretManagerServiceClient = new SecretManagerServiceClient();\ntry {\n    $formattedName = $secretManagerServiceClient-&gt;secretVersionName('[PROJECT]', '[SECRET]', '[SECRET_VERSION]');\n    $response = $secretManagerServiceClient-&gt;enableSecretVersion($formattedName);\n} finally {\n    $secretManagerServiceClient-&gt;close();\n}<\/code><\/pre>","examples":[],"resources":[],"params":[{"name":"name","description":"<p>Required. The resource name of the [SecretVersion][google.cloud.secretmanager.v1.SecretVersion] to enable in the format\n<code>projects\/&amp;#42;\/secrets\/&amp;#42;\/versions\/*<\/code>.<\/p>","types":["<a href=\"http:\/\/php.net\/manual\/en\/language.types.string.php\" target=\"_blank\">string<\/a>"],"optional":false,"nullable":null},{"name":"optionalArgs","description":"<p>Optional.<\/p>","types":["<a href=\"http:\/\/php.net\/manual\/en\/language.types.array.php\" target=\"_blank\">array<\/a>"],"optional":false,"nullable":null},{"name":"optionalArgs.retrySettings\n","description":"<p>Retry settings to use for this call. Can be a <a href=\"https:\/\/googleapis.github.io\/gax-php\/1.3.1\/Google\/ApiCore\/RetrySettings.html\" target=\"_blank\">Google\\ApiCore\\RetrySettings<\/a> object, or an associative array of retry settings parameters. See the documentation on <a href=\"https:\/\/googleapis.github.io\/gax-php\/1.3.1\/Google\/ApiCore\/RetrySettings.html\" target=\"_blank\">Google\\ApiCore\\RetrySettings<\/a> for example usage.<\/p>","types":["<a href=\"https:\/\/googleapis.github.io\/gax-php\/1.3.1\/Google\/ApiCore\/RetrySettings.html\" target=\"_blank\">Google\\ApiCore\\RetrySettings<\/a>","<a href=\"http:\/\/php.net\/manual\/en\/language.types.array.php\" target=\"_blank\">array<\/a>"],"optional":null,"nullable":null}],"exceptions":[{"type":"\\Google\\ApiCore\\ApiException","description":"if the remote call fails"}],"returns":[{"types":["<a data-custom-type=\"secretmanager\/v1\/secretversion\">Google\\Cloud\\SecretManager\\V1\\SecretVersion<\/a>"],"description":""}]},{"id":"destroySecretVersion","type":"instance","name":"destroySecretVersion","source":"SecretManager\/src\/V1\/Gapic\/SecretManagerServiceGapicClient.php#L1025","description":"<p>Destroys a [SecretVersion][google.cloud.secretmanager.v1.SecretVersion].<\/p>\n<p>Sets the [state][google.cloud.secretmanager.v1.SecretVersion.state] of the [SecretVersion][google.cloud.secretmanager.v1.SecretVersion] to\n[DESTROYED][google.cloud.secretmanager.v1.SecretVersion.State.DESTROYED] and irrevocably destroys the\nsecret data.<\/p>\n<p>Sample code:<\/p>\n<pre><code>$secretManagerServiceClient = new SecretManagerServiceClient();\ntry {\n    $formattedName = $secretManagerServiceClient-&gt;secretVersionName('[PROJECT]', '[SECRET]', '[SECRET_VERSION]');\n    $response = $secretManagerServiceClient-&gt;destroySecretVersion($formattedName);\n} finally {\n    $secretManagerServiceClient-&gt;close();\n}<\/code><\/pre>","examples":[],"resources":[],"params":[{"name":"name","description":"<p>Required. The resource name of the [SecretVersion][google.cloud.secretmanager.v1.SecretVersion] to destroy in the format\n<code>projects\/&amp;#42;\/secrets\/&amp;#42;\/versions\/*<\/code>.<\/p>","types":["<a href=\"http:\/\/php.net\/manual\/en\/language.types.string.php\" target=\"_blank\">string<\/a>"],"optional":false,"nullable":null},{"name":"optionalArgs","description":"<p>Optional.<\/p>","types":["<a href=\"http:\/\/php.net\/manual\/en\/language.types.array.php\" target=\"_blank\">array<\/a>"],"optional":false,"nullable":null},{"name":"optionalArgs.retrySettings\n","description":"<p>Retry settings to use for this call. Can be a <a href=\"https:\/\/googleapis.github.io\/gax-php\/1.3.1\/Google\/ApiCore\/RetrySettings.html\" target=\"_blank\">Google\\ApiCore\\RetrySettings<\/a> object, or an associative array of retry settings parameters. See the documentation on <a href=\"https:\/\/googleapis.github.io\/gax-php\/1.3.1\/Google\/ApiCore\/RetrySettings.html\" target=\"_blank\">Google\\ApiCore\\RetrySettings<\/a> for example usage.<\/p>","types":["<a href=\"https:\/\/googleapis.github.io\/gax-php\/1.3.1\/Google\/ApiCore\/RetrySettings.html\" target=\"_blank\">Google\\ApiCore\\RetrySettings<\/a>","<a href=\"http:\/\/php.net\/manual\/en\/language.types.array.php\" target=\"_blank\">array<\/a>"],"optional":null,"nullable":null}],"exceptions":[{"type":"\\Google\\ApiCore\\ApiException","description":"if the remote call fails"}],"returns":[{"types":["<a data-custom-type=\"secretmanager\/v1\/secretversion\">Google\\Cloud\\SecretManager\\V1\\SecretVersion<\/a>"],"description":""}]},{"id":"setIamPolicy","type":"instance","name":"setIamPolicy","source":"SecretManager\/src\/V1\/Gapic\/SecretManagerServiceGapicClient.php#L1084","description":"<p>Sets the access control policy on the specified secret. Replaces any\nexisting policy.<\/p>\n<p>Permissions on [SecretVersions][google.cloud.secretmanager.v1.SecretVersion] are enforced according\nto the policy set on the associated [Secret][google.cloud.secretmanager.v1.Secret].<\/p>\n<p>Sample code:<\/p>\n<pre><code>$secretManagerServiceClient = new SecretManagerServiceClient();\ntry {\n    $resource = '';\n    $policy = new Policy();\n    $response = $secretManagerServiceClient-&gt;setIamPolicy($resource, $policy);\n} finally {\n    $secretManagerServiceClient-&gt;close();\n}<\/code><\/pre>","examples":[],"resources":[],"params":[{"name":"resource","description":"<p>REQUIRED: The resource for which the policy is being specified.\nSee the operation documentation for the appropriate value for this field.<\/p>","types":["<a href=\"http:\/\/php.net\/manual\/en\/language.types.string.php\" target=\"_blank\">string<\/a>"],"optional":false,"nullable":null},{"name":"policy","description":"<p>REQUIRED: The complete policy to be applied to the <code>resource<\/code>. The size of\nthe policy is limited to a few 10s of KB. An empty policy is a\nvalid policy but certain Cloud Platform services (such as Projects)\nmight reject them.<\/p>","types":["<a href=\"https:\/\/googleapis.github.io\/gax-php\/1.3.1\/Google\/Cloud\/Iam\/V1\/Policy.html\" target=\"_blank\">Google\\Cloud\\Iam\\V1\\Policy<\/a>"],"optional":false,"nullable":null},{"name":"optionalArgs","description":"<p>Optional.<\/p>","types":["<a href=\"http:\/\/php.net\/manual\/en\/language.types.array.php\" target=\"_blank\">array<\/a>"],"optional":false,"nullable":null},{"name":"optionalArgs.retrySettings\n","description":"<p>Retry settings to use for this call. Can be a <a href=\"https:\/\/googleapis.github.io\/gax-php\/1.3.1\/Google\/ApiCore\/RetrySettings.html\" target=\"_blank\">Google\\ApiCore\\RetrySettings<\/a> object, or an associative array of retry settings parameters. See the documentation on <a href=\"https:\/\/googleapis.github.io\/gax-php\/1.3.1\/Google\/ApiCore\/RetrySettings.html\" target=\"_blank\">Google\\ApiCore\\RetrySettings<\/a> for example usage.<\/p>","types":["<a href=\"https:\/\/googleapis.github.io\/gax-php\/1.3.1\/Google\/ApiCore\/RetrySettings.html\" target=\"_blank\">Google\\ApiCore\\RetrySettings<\/a>","<a href=\"http:\/\/php.net\/manual\/en\/language.types.array.php\" target=\"_blank\">array<\/a>"],"optional":null,"nullable":null}],"exceptions":[{"type":"\\Google\\ApiCore\\ApiException","description":"if the remote call fails"}],"returns":[{"types":["<a href=\"https:\/\/googleapis.github.io\/gax-php\/1.3.1\/Google\/Cloud\/Iam\/V1\/Policy.html\" target=\"_blank\">Google\\Cloud\\Iam\\V1\\Policy<\/a>"],"description":""}]},{"id":"getIamPolicy","type":"instance","name":"getIamPolicy","source":"SecretManager\/src\/V1\/Gapic\/SecretManagerServiceGapicClient.php#L1139","description":"<p>Gets the access control policy for a secret.<\/p>\n<p>Returns empty policy if the secret exists and does not have a policy set.<\/p>\n<p>Sample code:<\/p>\n<pre><code>$secretManagerServiceClient = new SecretManagerServiceClient();\ntry {\n    $resource = '';\n    $response = $secretManagerServiceClient-&gt;getIamPolicy($resource);\n} finally {\n    $secretManagerServiceClient-&gt;close();\n}<\/code><\/pre>","examples":[],"resources":[],"params":[{"name":"resource","description":"<p>REQUIRED: The resource for which the policy is being requested.\nSee the operation documentation for the appropriate value for this field.<\/p>","types":["<a href=\"http:\/\/php.net\/manual\/en\/language.types.string.php\" target=\"_blank\">string<\/a>"],"optional":false,"nullable":null},{"name":"optionalArgs","description":"<p>Optional.<\/p>","types":["<a href=\"http:\/\/php.net\/manual\/en\/language.types.array.php\" target=\"_blank\">array<\/a>"],"optional":false,"nullable":null},{"name":"optionalArgs.options\n","description":"<p>OPTIONAL: A <code>GetPolicyOptions<\/code> object for specifying options to <code>GetIamPolicy<\/code>. This field is only used by Cloud IAM.<\/p>","types":["<a href=\"https:\/\/googleapis.github.io\/gax-php\/1.3.1\/Google\/Cloud\/Iam\/V1\/GetPolicyOptions.html\" target=\"_blank\">Google\\Cloud\\Iam\\V1\\GetPolicyOptions<\/a>"],"optional":null,"nullable":null},{"name":"optionalArgs.retrySettings\n","description":"<p>Retry settings to use for this call. Can be a <a href=\"https:\/\/googleapis.github.io\/gax-php\/1.3.1\/Google\/ApiCore\/RetrySettings.html\" target=\"_blank\">Google\\ApiCore\\RetrySettings<\/a> object, or an associative array of retry settings parameters. See the documentation on <a href=\"https:\/\/googleapis.github.io\/gax-php\/1.3.1\/Google\/ApiCore\/RetrySettings.html\" target=\"_blank\">Google\\ApiCore\\RetrySettings<\/a> for example usage.<\/p>","types":["<a href=\"https:\/\/googleapis.github.io\/gax-php\/1.3.1\/Google\/ApiCore\/RetrySettings.html\" target=\"_blank\">Google\\ApiCore\\RetrySettings<\/a>","<a href=\"http:\/\/php.net\/manual\/en\/language.types.array.php\" target=\"_blank\">array<\/a>"],"optional":null,"nullable":null}],"exceptions":[{"type":"\\Google\\ApiCore\\ApiException","description":"if the remote call fails"}],"returns":[{"types":["<a href=\"https:\/\/googleapis.github.io\/gax-php\/1.3.1\/Google\/Cloud\/Iam\/V1\/Policy.html\" target=\"_blank\">Google\\Cloud\\Iam\\V1\\Policy<\/a>"],"description":""}]},{"id":"testIamPermissions","type":"instance","name":"testIamPermissions","source":"SecretManager\/src\/V1\/Gapic\/SecretManagerServiceGapicClient.php#L1203","description":"<p>Returns permissions that a caller has for the specified secret.<\/p>\n<p>If the secret does not exist, this call returns an empty set of\npermissions, not a NOT_FOUND error.<\/p>\n<p>Note: This operation is designed to be used for building permission-aware\nUIs and command-line tools, not for authorization checking. This operation\nmay &quot;fail open&quot; without warning.<\/p>\n<p>Sample code:<\/p>\n<pre><code>$secretManagerServiceClient = new SecretManagerServiceClient();\ntry {\n    $resource = '';\n    $permissions = [];\n    $response = $secretManagerServiceClient-&gt;testIamPermissions($resource, $permissions);\n} finally {\n    $secretManagerServiceClient-&gt;close();\n}<\/code><\/pre>","examples":[],"resources":[],"params":[{"name":"resource","description":"<p>REQUIRED: The resource for which the policy detail is being requested.\nSee the operation documentation for the appropriate value for this field.<\/p>","types":["<a href=\"http:\/\/php.net\/manual\/en\/language.types.string.php\" target=\"_blank\">string<\/a>"],"optional":false,"nullable":null},{"name":"permissions","description":"<p>The set of permissions to check for the <code>resource<\/code>. Permissions with\nwildcards (such as '<em>' or 'storage.<\/em>') are not allowed. For more\ninformation see\n<a href=\"https:\/\/cloud.google.com\/iam\/docs\/overview#permissions\">IAM Overview<\/a>.<\/p>","types":["<a href=\"http:\/\/php.net\/manual\/en\/language.types.string.php\" target=\"_blank\">string[]<\/a>"],"optional":false,"nullable":null},{"name":"optionalArgs","description":"<p>Optional.<\/p>","types":["<a href=\"http:\/\/php.net\/manual\/en\/language.types.array.php\" target=\"_blank\">array<\/a>"],"optional":false,"nullable":null},{"name":"optionalArgs.retrySettings\n","description":"<p>Retry settings to use for this call. Can be a <a href=\"https:\/\/googleapis.github.io\/gax-php\/1.3.1\/Google\/ApiCore\/RetrySettings.html\" target=\"_blank\">Google\\ApiCore\\RetrySettings<\/a> object, or an associative array of retry settings parameters. See the documentation on <a href=\"https:\/\/googleapis.github.io\/gax-php\/1.3.1\/Google\/ApiCore\/RetrySettings.html\" target=\"_blank\">Google\\ApiCore\\RetrySettings<\/a> for example usage.<\/p>","types":["<a href=\"https:\/\/googleapis.github.io\/gax-php\/1.3.1\/Google\/ApiCore\/RetrySettings.html\" target=\"_blank\">Google\\ApiCore\\RetrySettings<\/a>","<a href=\"http:\/\/php.net\/manual\/en\/language.types.array.php\" target=\"_blank\">array<\/a>"],"optional":null,"nullable":null}],"exceptions":[{"type":"\\Google\\ApiCore\\ApiException","description":"if the remote call fails"}],"returns":[{"types":["<a href=\"https:\/\/googleapis.github.io\/gax-php\/1.3.1\/Google\/Cloud\/Iam\/V1\/TestIamPermissionsResponse.html\" target=\"_blank\">Google\\Cloud\\Iam\\V1\\TestIamPermissionsResponse<\/a>"],"description":""}]}]}