{"id":"documentai\/v1\/document\/entityrelation","type":"","title":"Google\\Cloud\\DocumentAI\\V1\\Document\\EntityRelation","name":"EntityRelation","description":"<p>Relationship between [Entities][google.cloud.documentai.v1.Document.Entity].<\/p>\n<p>Generated from protobuf message <code>google.cloud.documentai.v1.Document.EntityRelation<\/code><\/p>\n<p>Extends <a href=\"https:\/\/github.com\/protocolbuffers\/protobuf-php\/tree\/v3.21.6\/src\/Google\/Protobuf\/Internal\/Message.php\" target=\"_blank\">Google\\Protobuf\\Internal\\Message<\/a><\/p>","examples":[],"resources":[],"methods":[{"id":"__construct","type":"constructor","name":"__construct","source":"DocumentAi\/src\/V1\/Document\/EntityRelation.php#L51","description":"<p>Constructor.<\/p>","examples":[],"resources":[],"params":[{"name":"data","description":"<p>Optional. Data for populating the Message object.<\/p>","types":["<a href=\"http:\/\/php.net\/manual\/en\/language.types.array.php\" target=\"_blank\">array<\/a>"],"optional":false,"nullable":null},{"name":"data.subject_id\n","description":"<p>Subject entity id.<\/p>","types":["<a href=\"http:\/\/php.net\/manual\/en\/language.types.string.php\" target=\"_blank\">string<\/a>"],"optional":null,"nullable":null},{"name":"data.object_id\n","description":"<p>Object entity id.<\/p>","types":["<a href=\"http:\/\/php.net\/manual\/en\/language.types.string.php\" target=\"_blank\">string<\/a>"],"optional":null,"nullable":null},{"name":"data.relation\n","description":"<p>Relationship description.<\/p>","types":["<a href=\"http:\/\/php.net\/manual\/en\/language.types.string.php\" target=\"_blank\">string<\/a>"],"optional":null,"nullable":null}],"exceptions":[],"returns":[]},{"id":"getSubjectId","type":"instance","name":"getSubjectId","source":"DocumentAi\/src\/V1\/Document\/EntityRelation.php#L62","description":"<p>Subject entity id.<\/p>\n<p>Generated from protobuf field <code>string subject_id = 1;<\/code><\/p>","examples":[],"resources":[],"params":[],"exceptions":[],"returns":[{"types":["<a href=\"http:\/\/php.net\/manual\/en\/language.types.string.php\" target=\"_blank\">string<\/a>"],"description":""}]},{"id":"setSubjectId","type":"instance","name":"setSubjectId","source":"DocumentAi\/src\/V1\/Document\/EntityRelation.php#L74","description":"<p>Subject entity id.<\/p>\n<p>Generated from protobuf field <code>string subject_id = 1;<\/code><\/p>","examples":[],"resources":[],"params":[{"name":"var","description":"<p>Subject entity id.<\/p>\n","types":["<a href=\"http:\/\/php.net\/manual\/en\/language.types.string.php\" target=\"_blank\">string<\/a>"],"optional":false,"nullable":null}],"exceptions":[],"returns":[{"types":["<a data-custom-type=\"documentai\/v1\/document\/entityrelation\">Google\\Cloud\\DocumentAI\\V1\\Document\\EntityRelation<\/a>"],"description":""}]},{"id":"getObjectId","type":"instance","name":"getObjectId","source":"DocumentAi\/src\/V1\/Document\/EntityRelation.php#L88","description":"<p>Object entity id.<\/p>\n<p>Generated from protobuf field <code>string object_id = 2;<\/code><\/p>","examples":[],"resources":[],"params":[],"exceptions":[],"returns":[{"types":["<a href=\"http:\/\/php.net\/manual\/en\/language.types.string.php\" target=\"_blank\">string<\/a>"],"description":""}]},{"id":"setObjectId","type":"instance","name":"setObjectId","source":"DocumentAi\/src\/V1\/Document\/EntityRelation.php#L100","description":"<p>Object entity id.<\/p>\n<p>Generated from protobuf field <code>string object_id = 2;<\/code><\/p>","examples":[],"resources":[],"params":[{"name":"var","description":"<p>Object entity id.<\/p>\n","types":["<a href=\"http:\/\/php.net\/manual\/en\/language.types.string.php\" target=\"_blank\">string<\/a>"],"optional":false,"nullable":null}],"exceptions":[],"returns":[{"types":["<a data-custom-type=\"documentai\/v1\/document\/entityrelation\">Google\\Cloud\\DocumentAI\\V1\\Document\\EntityRelation<\/a>"],"description":""}]},{"id":"getRelation","type":"instance","name":"getRelation","source":"DocumentAi\/src\/V1\/Document\/EntityRelation.php#L114","description":"<p>Relationship description.<\/p>\n<p>Generated from protobuf field <code>string relation = 3;<\/code><\/p>","examples":[],"resources":[],"params":[],"exceptions":[],"returns":[{"types":["<a href=\"http:\/\/php.net\/manual\/en\/language.types.string.php\" target=\"_blank\">string<\/a>"],"description":""}]},{"id":"setRelation","type":"instance","name":"setRelation","source":"DocumentAi\/src\/V1\/Document\/EntityRelation.php#L126","description":"<p>Relationship description.<\/p>\n<p>Generated from protobuf field <code>string relation = 3;<\/code><\/p>","examples":[],"resources":[],"params":[{"name":"var","description":"<p>Relationship description.<\/p>\n","types":["<a href=\"http:\/\/php.net\/manual\/en\/language.types.string.php\" target=\"_blank\">string<\/a>"],"optional":false,"nullable":null}],"exceptions":[],"returns":[{"types":["<a data-custom-type=\"documentai\/v1\/document\/entityrelation\">Google\\Cloud\\DocumentAI\\V1\\Document\\EntityRelation<\/a>"],"description":""}]}]}